split_command_line/__init__.py
split_command_line/__main__.py
split_command_line-0.1.0a0.dist-info/licenses/LICENSE
split_command_line-0.1.0a0.dist-info/METADATA
split_command_line-0.1.0a0.dist-info/WHEEL
split_command_line-0.1.0a0.dist-info/top_level.txt
split_command_line-0.1.0a0.dist-info/RECORD
