Metadata-Version: 2.4
Name: split-command-line
Version: 0.1.0a0
Summary: A Python library for splitting command-line arguments according to NT (Windows) and POSIX (Unix) rules. Like `shlex.split` but with NT support and without shell features.
Author-email: Jifeng Wu <jifengwu2k@gmail.com>
License-Expression: MIT
Project-URL: Homepage, https://github.com/jifengwu2k/split-command-line
Project-URL: Bug Tracker, https://github.com/jifengwu2k/split-command-line/issues
Classifier: Programming Language :: Python :: 2
Classifier: Programming Language :: Python :: 3
Classifier: Operating System :: OS Independent
Requires-Python: >=2
License-File: LICENSE
Dynamic: license-file
